odoo10_addon_account_payment_widget_amount-10.0.1.0.0.99.dev3-py2.7-nspkg.pth
odoo/addons/account_payment_widget_amount/README.rst
odoo/addons/account_payment_widget_amount/__init__.py
odoo/addons/account_payment_widget_amount/__manifest__.py
odoo/addons/account_payment_widget_amount/i18n/account_payment_widget_amount.pot
odoo/addons/account_payment_widget_amount/models/__init__.py
odoo/addons/account_payment_widget_amount/models/account_move_line.py
odoo/addons/account_payment_widget_amount/static/description/icon.png
odoo/addons/account_payment_widget_amount/static/description/payment_widget.png
odoo/addons/account_payment_widget_amount/static/description/payment_widget_amount_reconciled.png
odoo/addons/account_payment_widget_amount/static/src/js/account_payment_widget.js
odoo/addons/account_payment_widget_amount/static/src/xml/account_payment.xml
odoo/addons/account_payment_widget_amount/tests/__init__.py
odoo/addons/account_payment_widget_amount/tests/test_account_payment_widget_amount.py
odoo/addons/account_payment_widget_amount/views/account.xml
odoo10_addon_account_payment_widget_amount-10.0.1.0.0.99.dev3.dist-info/METADATA
odoo10_addon_account_payment_widget_amount-10.0.1.0.0.99.dev3.dist-info/RECORD
odoo10_addon_account_payment_widget_amount-10.0.1.0.0.99.dev3.dist-info/WHEEL
odoo10_addon_account_payment_widget_amount-10.0.1.0.0.99.dev3.dist-info/namespace_packages.txt
odoo10_addon_account_payment_widget_amount-10.0.1.0.0.99.dev3.dist-info/top_level.txt
